<annotation>
	<folder>2</folder>
	<filename>md0497_Image_014.jpg</filename>
	<path>C:\Users\Yuan\Desktop\mask\2\md0497_Image_014.jpg</path>
	<source>
		<database>Unknown</database>
	</source>
	<size>
		<width>880</width>
		<height>650</height>
		<depth>3</depth>
	</size>
	<segmented>0</segmented>
	<object>
		<name>BIRADS_3</name>
		<pose>Unspecified</pose>
		<truncated>0</truncated>
		<difficult>0</difficult>
		<bndbox>
			<xmin>33</xmin>
			<ymin>150</ymin>
			<xmax>233</xmax>
			<ymax>350</ymax>
		</bndbox>
	</object>
	<object>
		<name>BIRADS_2</name>
		<pose>Unspecified</pose>
		<truncated>0</truncated>
		<difficult>0</difficult>
		<bndbox>
			<xmin>389</xmin>
			<ymin>175</ymin>
			<xmax>589</xmax>
			<ymax>375</ymax>
		</bndbox>
	</object>
	<segment>
		<name>BIRADS_3</name>
		<pose>Unspecified</pose>
		<truncated>0</truncated>
		<difficult>0</difficult>
		<count>225</count>
		<segreg>
			<pt_0>198 240</pt_0>
			<pt_1>198 241</pt_1>
			<pt_2>198 240</pt_2>
			<pt_3>198 240</pt_3>
			<pt_4>198 240</pt_4>
			<pt_5>198 240</pt_5>
			<pt_6>198 240</pt_6>
			<pt_7>198 240</pt_7>
			<pt_8>186 246</pt_8>
			<pt_9>185 246</pt_9>
			<pt_10>184 246</pt_10>
			<pt_11>183 246</pt_11>
			<pt_12>182 246</pt_12>
			<pt_13>182 247</pt_13>
			<pt_14>181 247</pt_14>
			<pt_15>180 247</pt_15>
			<pt_16>179 247</pt_16>
			<pt_17>178 247</pt_17>
			<pt_18>177 247</pt_18>
			<pt_19>176 248</pt_19>
			<pt_20>175 248</pt_20>
			<pt_21>174 248</pt_21>
			<pt_22>173 248</pt_22>
			<pt_23>172 248</pt_23>
			<pt_24>171 248</pt_24>
			<pt_25>170 248</pt_25>
			<pt_26>168 248</pt_26>
			<pt_27>166 248</pt_27>
			<pt_28>165 248</pt_28>
			<pt_29>165 249</pt_29>
			<pt_30>163 249</pt_30>
			<pt_31>162 249</pt_31>
			<pt_32>161 249</pt_32>
			<pt_33>160 249</pt_33>
			<pt_34>159 249</pt_34>
			<pt_35>158 249</pt_35>
			<pt_36>157 249</pt_36>
			<pt_37>156 249</pt_37>
			<pt_38>155 249</pt_38>
			<pt_39>154 249</pt_39>
			<pt_40>152 249</pt_40>
			<pt_41>151 249</pt_41>
			<pt_42>150 249</pt_42>
			<pt_43>149 249</pt_43>
			<pt_44>148 249</pt_44>
			<pt_45>147 249</pt_45>
			<pt_46>146 249</pt_46>
			<pt_47>144 249</pt_47>
			<pt_48>143 249</pt_48>
			<pt_49>142 249</pt_49>
			<pt_50>141 249</pt_50>
			<pt_51>140 248</pt_51>
			<pt_52>139 248</pt_52>
			<pt_53>138 248</pt_53>
			<pt_54>137 247</pt_54>
			<pt_55>136 247</pt_55>
			<pt_56>135 247</pt_56>
			<pt_57>134 247</pt_57>
			<pt_58>133 247</pt_58>
			<pt_59>132 247</pt_59>
			<pt_60>131 247</pt_60>
			<pt_61>130 247</pt_61>
			<pt_62>129 247</pt_62>
			<pt_63>129 247</pt_63>
			<pt_64>128 247</pt_64>
			<pt_65>127 247</pt_65>
			<pt_66>126 247</pt_66>
			<pt_67>125 247</pt_67>
			<pt_68>124 247</pt_68>
			<pt_69>123 247</pt_69>
			<pt_70>123 246</pt_70>
			<pt_71>122 246</pt_71>
			<pt_72>120 246</pt_72>
			<pt_73>119 246</pt_73>
			<pt_74>118 246</pt_74>
			<pt_75>117 246</pt_75>
			<pt_76>115 245</pt_76>
			<pt_77>114 245</pt_77>
			<pt_78>113 244</pt_78>
			<pt_79>112 244</pt_79>
			<pt_80>111 244</pt_80>
			<pt_81>111 243</pt_81>
			<pt_82>110 243</pt_82>
			<pt_83>109 243</pt_83>
			<pt_84>108 243</pt_84>
			<pt_85>108 242</pt_85>
			<pt_86>107 242</pt_86>
			<pt_87>107 241</pt_87>
			<pt_88>106 241</pt_88>
			<pt_89>105 241</pt_89>
			<pt_90>104 241</pt_90>
			<pt_91>103 241</pt_91>
			<pt_92>102 240</pt_92>
			<pt_93>101 240</pt_93>
			<pt_94>100 240</pt_94>
			<pt_95>99 240</pt_95>
			<pt_96>98 240</pt_96>
			<pt_97>97 240</pt_97>
			<pt_98>95 240</pt_98>
			<pt_99>94 240</pt_99>
			<pt_100>92 240</pt_100>
			<pt_101>91 240</pt_101>
			<pt_102>90 240</pt_102>
			<pt_103>89 240</pt_103>
			<pt_104>88 240</pt_104>
			<pt_105>86 240</pt_105>
			<pt_106>85 240</pt_106>
			<pt_107>84 240</pt_107>
			<pt_108>84 239</pt_108>
			<pt_109>83 238</pt_109>
			<pt_110>82 238</pt_110>
			<pt_111>82 237</pt_111>
			<pt_112>81 236</pt_112>
			<pt_113>81 235</pt_113>
			<pt_114>81 234</pt_114>
			<pt_115>81 233</pt_115>
			<pt_116>81 232</pt_116>
			<pt_117>81 231</pt_117>
			<pt_118>81 230</pt_118>
			<pt_119>81 229</pt_119>
			<pt_120>82 228</pt_120>
			<pt_121>83 227</pt_121>
			<pt_122>84 227</pt_122>
			<pt_123>85 227</pt_123>
			<pt_124>86 227</pt_124>
			<pt_125>87 227</pt_125>
			<pt_126>88 227</pt_126>
			<pt_127>89 227</pt_127>
			<pt_128>91 227</pt_128>
			<pt_129>92 227</pt_129>
			<pt_130>93 227</pt_130>
			<pt_131>94 227</pt_131>
			<pt_132>95 227</pt_132>
			<pt_133>96 227</pt_133>
			<pt_134>97 227</pt_134>
			<pt_135>98 227</pt_135>
			<pt_136>100 227</pt_136>
			<pt_137>101 227</pt_137>
			<pt_138>102 227</pt_138>
			<pt_139>103 227</pt_139>
			<pt_140>104 227</pt_140>
			<pt_141>105 227</pt_141>
			<pt_142>107 227</pt_142>
			<pt_143>108 227</pt_143>
			<pt_144>110 227</pt_144>
			<pt_145>111 227</pt_145>
			<pt_146>112 227</pt_146>
			<pt_147>113 227</pt_147>
			<pt_148>115 227</pt_148>
			<pt_149>116 227</pt_149>
			<pt_150>117 227</pt_150>
			<pt_151>119 226</pt_151>
			<pt_152>119 226</pt_152>
			<pt_153>120 226</pt_153>
			<pt_154>121 226</pt_154>
			<pt_155>123 226</pt_155>
			<pt_156>124 226</pt_156>
			<pt_157>125 226</pt_157>
			<pt_158>126 226</pt_158>
			<pt_159>127 226</pt_159>
			<pt_160>128 226</pt_160>
			<pt_161>130 226</pt_161>
			<pt_162>131 225</pt_162>
			<pt_163>133 225</pt_163>
			<pt_164>133 224</pt_164>
			<pt_165>134 224</pt_165>
			<pt_166>135 224</pt_166>
			<pt_167>136 224</pt_167>
			<pt_168>137 224</pt_168>
			<pt_169>138 224</pt_169>
			<pt_170>139 224</pt_170>
			<pt_171>140 224</pt_171>
			<pt_172>141 224</pt_172>
			<pt_173>142 224</pt_173>
			<pt_174>143 224</pt_174>
			<pt_175>144 224</pt_175>
			<pt_176>145 224</pt_176>
			<pt_177>146 224</pt_177>
			<pt_178>148 224</pt_178>
			<pt_179>149 224</pt_179>
			<pt_180>151 225</pt_180>
			<pt_181>153 225</pt_181>
			<pt_182>155 226</pt_182>
			<pt_183>156 226</pt_183>
			<pt_184>158 227</pt_184>
			<pt_185>159 227</pt_185>
			<pt_186>160 227</pt_186>
			<pt_187>161 227</pt_187>
			<pt_188>162 228</pt_188>
			<pt_189>163 228</pt_189>
			<pt_190>164 229</pt_190>
			<pt_191>165 229</pt_191>
			<pt_192>166 229</pt_192>
			<pt_193>167 230</pt_193>
			<pt_194>168 230</pt_194>
			<pt_195>169 230</pt_195>
			<pt_196>170 230</pt_196>
			<pt_197>171 231</pt_197>
			<pt_198>172 231</pt_198>
			<pt_199>174 231</pt_199>
			<pt_200>175 231</pt_200>
			<pt_201>177 232</pt_201>
			<pt_202>178 232</pt_202>
			<pt_203>179 232</pt_203>
			<pt_204>180 232</pt_204>
			<pt_205>181 232</pt_205>
			<pt_206>182 232</pt_206>
			<pt_207>183 232</pt_207>
			<pt_208>183 233</pt_208>
			<pt_209>184 233</pt_209>
			<pt_210>186 233</pt_210>
			<pt_211>187 233</pt_211>
			<pt_212>188 233</pt_212>
			<pt_213>189 233</pt_213>
			<pt_214>198 240</pt_214>
			<pt_215>198 240</pt_215>
			<pt_216>198 240</pt_216>
			<pt_217>198 240</pt_217>
			<pt_218>198 240</pt_218>
			<pt_219>198 240</pt_219>
			<pt_220>198 240</pt_220>
			<pt_221>198 240</pt_221>
			<pt_222>198 240</pt_222>
			<pt_223>198 240</pt_223>
			<pt_224>198 240</pt_224>
		</segreg>
	</segment>
	<segment>
		<name>BIRADS_2</name>
		<pose>Unspecified</pose>
		<truncated>0</truncated>
		<difficult>0</difficult>
		<count>247</count>
		<segreg>
			<pt_0>568 222</pt_0>
			<pt_1>568 223</pt_1>
			<pt_2>568 222</pt_2>
			<pt_3>568 222</pt_3>
			<pt_4>568 222</pt_4>
			<pt_5>568 222</pt_5>
			<pt_6>568 222</pt_6>
			<pt_7>568 222</pt_7>
			<pt_8>568 222</pt_8>
			<pt_9>557 226</pt_9>
			<pt_10>556 226</pt_10>
			<pt_11>555 226</pt_11>
			<pt_12>552 226</pt_12>
			<pt_13>551 226</pt_13>
			<pt_14>550 226</pt_14>
			<pt_15>549 226</pt_15>
			<pt_16>549 227</pt_16>
			<pt_17>548 227</pt_17>
			<pt_18>547 227</pt_18>
			<pt_19>546 227</pt_19>
			<pt_20>545 227</pt_20>
			<pt_21>544 228</pt_21>
			<pt_22>543 228</pt_22>
			<pt_23>542 228</pt_23>
			<pt_24>541 228</pt_24>
			<pt_25>540 229</pt_25>
			<pt_26>539 229</pt_26>
			<pt_27>538 229</pt_27>
			<pt_28>537 229</pt_28>
			<pt_29>536 229</pt_29>
			<pt_30>535 229</pt_30>
			<pt_31>534 229</pt_31>
			<pt_32>533 229</pt_32>
			<pt_33>532 229</pt_33>
			<pt_34>531 229</pt_34>
			<pt_35>530 229</pt_35>
			<pt_36>529 229</pt_36>
			<pt_37>528 229</pt_37>
			<pt_38>527 229</pt_38>
			<pt_39>526 229</pt_39>
			<pt_40>525 229</pt_40>
			<pt_41>524 229</pt_41>
			<pt_42>523 229</pt_42>
			<pt_43>522 229</pt_43>
			<pt_44>521 229</pt_44>
			<pt_45>519 229</pt_45>
			<pt_46>519 229</pt_46>
			<pt_47>518 229</pt_47>
			<pt_48>517 229</pt_48>
			<pt_49>516 229</pt_49>
			<pt_50>515 229</pt_50>
			<pt_51>514 229</pt_51>
			<pt_52>513 229</pt_52>
			<pt_53>512 229</pt_53>
			<pt_54>510 229</pt_54>
			<pt_55>508 229</pt_55>
			<pt_56>507 229</pt_56>
			<pt_57>506 229</pt_57>
			<pt_58>504 229</pt_58>
			<pt_59>502 229</pt_59>
			<pt_60>500 229</pt_60>
			<pt_61>499 229</pt_61>
			<pt_62>498 229</pt_62>
			<pt_63>497 229</pt_63>
			<pt_64>496 229</pt_64>
			<pt_65>495 229</pt_65>
			<pt_66>494 229</pt_66>
			<pt_67>493 229</pt_67>
			<pt_68>492 229</pt_68>
			<pt_69>491 229</pt_69>
			<pt_70>490 229</pt_70>
			<pt_71>489 229</pt_71>
			<pt_72>488 229</pt_72>
			<pt_73>487 229</pt_73>
			<pt_74>486 229</pt_74>
			<pt_75>485 229</pt_75>
			<pt_76>484 229</pt_76>
			<pt_77>482 229</pt_77>
			<pt_78>480 229</pt_78>
			<pt_79>479 229</pt_79>
			<pt_80>478 229</pt_80>
			<pt_81>476 230</pt_81>
			<pt_82>475 230</pt_82>
			<pt_83>474 230</pt_83>
			<pt_84>473 230</pt_84>
			<pt_85>472 230</pt_85>
			<pt_86>471 230</pt_86>
			<pt_87>469 230</pt_87>
			<pt_88>468 230</pt_88>
			<pt_89>466 230</pt_89>
			<pt_90>465 230</pt_90>
			<pt_91>464 230</pt_91>
			<pt_92>463 230</pt_92>
			<pt_93>462 230</pt_93>
			<pt_94>460 230</pt_94>
			<pt_95>459 230</pt_95>
			<pt_96>458 230</pt_96>
			<pt_97>457 230</pt_97>
			<pt_98>456 230</pt_98>
			<pt_99>455 230</pt_99>
			<pt_100>454 230</pt_100>
			<pt_101>453 230</pt_101>
			<pt_102>452 230</pt_102>
			<pt_103>451 230</pt_103>
			<pt_104>451 229</pt_104>
			<pt_105>450 229</pt_105>
			<pt_106>450 228</pt_106>
			<pt_107>450 227</pt_107>
			<pt_108>450 226</pt_108>
			<pt_109>449 226</pt_109>
			<pt_110>449 225</pt_110>
			<pt_111>449 224</pt_111>
			<pt_112>449 223</pt_112>
			<pt_113>449 222</pt_113>
			<pt_114>448 221</pt_114>
			<pt_115>448 220</pt_115>
			<pt_116>448 219</pt_116>
			<pt_117>448 218</pt_117>
			<pt_118>448 217</pt_118>
			<pt_119>448 216</pt_119>
			<pt_120>449 215</pt_120>
			<pt_121>450 215</pt_121>
			<pt_122>450 214</pt_122>
			<pt_123>451 214</pt_123>
			<pt_124>452 214</pt_124>
			<pt_125>453 214</pt_125>
			<pt_126>455 213</pt_126>
			<pt_127>456 213</pt_127>
			<pt_128>456 212</pt_128>
			<pt_129>457 212</pt_129>
			<pt_130>458 212</pt_130>
			<pt_131>459 212</pt_131>
			<pt_132>460 212</pt_132>
			<pt_133>461 212</pt_133>
			<pt_134>463 212</pt_134>
			<pt_135>464 212</pt_135>
			<pt_136>465 212</pt_136>
			<pt_137>466 212</pt_137>
			<pt_138>467 212</pt_138>
			<pt_139>468 212</pt_139>
			<pt_140>469 212</pt_140>
			<pt_141>470 212</pt_141>
			<pt_142>471 212</pt_142>
			<pt_143>472 212</pt_143>
			<pt_144>473 211</pt_144>
			<pt_145>474 210</pt_145>
			<pt_146>475 209</pt_146>
			<pt_147>476 209</pt_147>
			<pt_148>476 208</pt_148>
			<pt_149>476 207</pt_149>
			<pt_150>477 207</pt_150>
			<pt_151>478 206</pt_151>
			<pt_152>479 206</pt_152>
			<pt_153>480 205</pt_153>
			<pt_154>481 204</pt_154>
			<pt_155>482 204</pt_155>
			<pt_156>483 204</pt_156>
			<pt_157>484 203</pt_157>
			<pt_158>485 203</pt_158>
			<pt_159>486 203</pt_159>
			<pt_160>487 203</pt_160>
			<pt_161>488 203</pt_161>
			<pt_162>489 203</pt_162>
			<pt_163>490 203</pt_163>
			<pt_164>491 203</pt_164>
			<pt_165>492 203</pt_165>
			<pt_166>493 203</pt_166>
			<pt_167>494 203</pt_167>
			<pt_168>495 203</pt_168>
			<pt_169>497 202</pt_169>
			<pt_170>498 202</pt_170>
			<pt_171>499 201</pt_171>
			<pt_172>500 201</pt_172>
			<pt_173>501 201</pt_173>
			<pt_174>502 201</pt_174>
			<pt_175>503 200</pt_175>
			<pt_176>504 200</pt_176>
			<pt_177>505 200</pt_177>
			<pt_178>506 200</pt_178>
			<pt_179>507 199</pt_179>
			<pt_180>508 199</pt_180>
			<pt_181>509 198</pt_181>
			<pt_182>510 198</pt_182>
			<pt_183>511 198</pt_183>
			<pt_184>513 198</pt_184>
			<pt_185>514 197</pt_185>
			<pt_186>515 196</pt_186>
			<pt_187>516 196</pt_187>
			<pt_188>517 196</pt_188>
			<pt_189>518 196</pt_189>
			<pt_190>519 196</pt_190>
			<pt_191>519 196</pt_191>
			<pt_192>520 196</pt_192>
			<pt_193>521 196</pt_193>
			<pt_194>523 196</pt_194>
			<pt_195>525 196</pt_195>
			<pt_196>526 196</pt_196>
			<pt_197>529 195</pt_197>
			<pt_198>530 195</pt_198>
			<pt_199>531 195</pt_199>
			<pt_200>532 195</pt_200>
			<pt_201>533 195</pt_201>
			<pt_202>534 195</pt_202>
			<pt_203>535 195</pt_203>
			<pt_204>536 195</pt_204>
			<pt_205>537 195</pt_205>
			<pt_206>538 195</pt_206>
			<pt_207>539 195</pt_207>
			<pt_208>540 195</pt_208>
			<pt_209>541 196</pt_209>
			<pt_210>542 196</pt_210>
			<pt_211>543 196</pt_211>
			<pt_212>544 196</pt_212>
			<pt_213>546 197</pt_213>
			<pt_214>547 197</pt_214>
			<pt_215>548 197</pt_215>
			<pt_216>549 198</pt_216>
			<pt_217>550 198</pt_217>
			<pt_218>551 199</pt_218>
			<pt_219>552 200</pt_219>
			<pt_220>553 200</pt_220>
			<pt_221>554 201</pt_221>
			<pt_222>554 202</pt_222>
			<pt_223>555 202</pt_223>
			<pt_224>556 202</pt_224>
			<pt_225>557 203</pt_225>
			<pt_226>558 203</pt_226>
			<pt_227>559 204</pt_227>
			<pt_228>560 204</pt_228>
			<pt_229>560 205</pt_229>
			<pt_230>561 205</pt_230>
			<pt_231>562 205</pt_231>
			<pt_232>563 206</pt_232>
			<pt_233>564 206</pt_233>
			<pt_234>564 207</pt_234>
			<pt_235>565 207</pt_235>
			<pt_236>566 208</pt_236>
			<pt_237>566 209</pt_237>
			<pt_238>567 209</pt_238>
			<pt_239>567 211</pt_239>
			<pt_240>568 222</pt_240>
			<pt_241>568 222</pt_241>
			<pt_242>568 222</pt_242>
			<pt_243>568 222</pt_243>
			<pt_244>568 222</pt_244>
			<pt_245>568 222</pt_245>
			<pt_246>568 222</pt_246>
		</segreg>
	</segment>
</annotation>
