<annotation>
	<folder>2</folder>
	<filename>md0473_Image_004.jpg</filename>
	<path>C:\Users\Yuan\Desktop\mask\2\md0473_Image_004.jpg</path>
	<source>
		<database>Unknown</database>
	</source>
	<size>
		<width>880</width>
		<height>650</height>
		<depth>3</depth>
	</size>
	<segmented>0</segmented>
	<object>
		<name>BIRADS_2</name>
		<pose>Unspecified</pose>
		<truncated>0</truncated>
		<difficult>0</difficult>
		<bndbox>
			<xmin>30</xmin>
			<ymin>153</ymin>
			<xmax>230</xmax>
			<ymax>353</ymax>
		</bndbox>
	</object>
	<object>
		<name>BIRADS_2</name>
		<pose>Unspecified</pose>
		<truncated>0</truncated>
		<difficult>0</difficult>
		<bndbox>
			<xmin>384</xmin>
			<ymin>172</ymin>
			<xmax>584</xmax>
			<ymax>372</ymax>
		</bndbox>
	</object>
	<segment>
		<name>BIRADS_2</name>
		<pose>Unspecified</pose>
		<truncated>0</truncated>
		<difficult>0</difficult>
		<count>181</count>
		<segreg>
			<pt_0>120 234</pt_0>
			<pt_1>119 234</pt_1>
			<pt_2>120 234</pt_2>
			<pt_3>120 234</pt_3>
			<pt_4>120 234</pt_4>
			<pt_5>120 234</pt_5>
			<pt_6>120 234</pt_6>
			<pt_7>120 234</pt_7>
			<pt_8>120 234</pt_8>
			<pt_9>120 234</pt_9>
			<pt_10>109 234</pt_10>
			<pt_11>108 234</pt_11>
			<pt_12>107 234</pt_12>
			<pt_13>106 235</pt_13>
			<pt_14>105 235</pt_14>
			<pt_15>104 235</pt_15>
			<pt_16>103 235</pt_16>
			<pt_17>102 235</pt_17>
			<pt_18>101 235</pt_18>
			<pt_19>100 235</pt_19>
			<pt_20>99 235</pt_20>
			<pt_21>98 236</pt_21>
			<pt_22>97 236</pt_22>
			<pt_23>96 236</pt_23>
			<pt_24>96 237</pt_24>
			<pt_25>96 238</pt_25>
			<pt_26>95 239</pt_26>
			<pt_27>95 240</pt_27>
			<pt_28>94 241</pt_28>
			<pt_29>94 242</pt_29>
			<pt_30>93 242</pt_30>
			<pt_31>92 243</pt_31>
			<pt_32>91 243</pt_32>
			<pt_33>90 243</pt_33>
			<pt_34>89 243</pt_34>
			<pt_35>88 243</pt_35>
			<pt_36>87 243</pt_36>
			<pt_37>86 243</pt_37>
			<pt_38>85 243</pt_38>
			<pt_39>84 243</pt_39>
			<pt_40>83 243</pt_40>
			<pt_41>82 243</pt_41>
			<pt_42>81 243</pt_42>
			<pt_43>80 243</pt_43>
			<pt_44>79 243</pt_44>
			<pt_45>78 243</pt_45>
			<pt_46>77 243</pt_46>
			<pt_47>76 243</pt_47>
			<pt_48>75 243</pt_48>
			<pt_49>74 243</pt_49>
			<pt_50>73 243</pt_50>
			<pt_51>72 243</pt_51>
			<pt_52>71 243</pt_52>
			<pt_53>70 243</pt_53>
			<pt_54>69 243</pt_54>
			<pt_55>68 243</pt_55>
			<pt_56>67 243</pt_56>
			<pt_57>66 243</pt_57>
			<pt_58>65 243</pt_58>
			<pt_59>64 243</pt_59>
			<pt_60>63 243</pt_60>
			<pt_61>62 243</pt_61>
			<pt_62>61 243</pt_62>
			<pt_63>60 243</pt_63>
			<pt_64>59 243</pt_64>
			<pt_65>58 243</pt_65>
			<pt_66>57 243</pt_66>
			<pt_67>56 243</pt_67>
			<pt_68>55 243</pt_68>
			<pt_69>54 243</pt_69>
			<pt_70>53 243</pt_70>
			<pt_71>52 242</pt_71>
			<pt_72>51 241</pt_72>
			<pt_73>50 241</pt_73>
			<pt_74>49 241</pt_74>
			<pt_75>48 240</pt_75>
			<pt_76>47 239</pt_76>
			<pt_77>47 238</pt_77>
			<pt_78>47 237</pt_78>
			<pt_79>46 236</pt_79>
			<pt_80>45 235</pt_80>
			<pt_81>45 234</pt_81>
			<pt_82>45 233</pt_82>
			<pt_83>45 232</pt_83>
			<pt_84>45 231</pt_84>
			<pt_85>45 230</pt_85>
			<pt_86>45 229</pt_86>
			<pt_87>45 228</pt_87>
			<pt_88>45 227</pt_88>
			<pt_89>45 226</pt_89>
			<pt_90>46 225</pt_90>
			<pt_91>46 224</pt_91>
			<pt_92>47 224</pt_92>
			<pt_93>47 223</pt_93>
			<pt_94>47 222</pt_94>
			<pt_95>48 221</pt_95>
			<pt_96>49 220</pt_96>
			<pt_97>50 218</pt_97>
			<pt_98>51 217</pt_98>
			<pt_99>52 217</pt_99>
			<pt_100>52 215</pt_100>
			<pt_101>53 215</pt_101>
			<pt_102>53 214</pt_102>
			<pt_103>54 214</pt_103>
			<pt_104>55 213</pt_104>
			<pt_105>56 212</pt_105>
			<pt_106>58 212</pt_106>
			<pt_107>59 212</pt_107>
			<pt_108>60 212</pt_108>
			<pt_109>61 212</pt_109>
			<pt_110>62 212</pt_110>
			<pt_111>63 212</pt_111>
			<pt_112>64 212</pt_112>
			<pt_113>65 212</pt_113>
			<pt_114>66 212</pt_114>
			<pt_115>67 212</pt_115>
			<pt_116>68 212</pt_116>
			<pt_117>69 212</pt_117>
			<pt_118>70 212</pt_118>
			<pt_119>71 212</pt_119>
			<pt_120>72 212</pt_120>
			<pt_121>73 212</pt_121>
			<pt_122>74 212</pt_122>
			<pt_123>75 212</pt_123>
			<pt_124>76 212</pt_124>
			<pt_125>77 212</pt_125>
			<pt_126>78 212</pt_126>
			<pt_127>79 212</pt_127>
			<pt_128>81 212</pt_128>
			<pt_129>82 212</pt_129>
			<pt_130>83 212</pt_130>
			<pt_131>84 212</pt_131>
			<pt_132>85 212</pt_132>
			<pt_133>86 212</pt_133>
			<pt_134>87 212</pt_134>
			<pt_135>88 212</pt_135>
			<pt_136>89 212</pt_136>
			<pt_137>90 213</pt_137>
			<pt_138>91 213</pt_138>
			<pt_139>92 213</pt_139>
			<pt_140>93 213</pt_140>
			<pt_141>94 213</pt_141>
			<pt_142>95 214</pt_142>
			<pt_143>96 215</pt_143>
			<pt_144>97 215</pt_144>
			<pt_145>98 215</pt_145>
			<pt_146>98 216</pt_146>
			<pt_147>99 216</pt_147>
			<pt_148>100 217</pt_148>
			<pt_149>101 217</pt_149>
			<pt_150>102 218</pt_150>
			<pt_151>103 218</pt_151>
			<pt_152>104 218</pt_152>
			<pt_153>105 219</pt_153>
			<pt_154>106 219</pt_154>
			<pt_155>107 219</pt_155>
			<pt_156>108 219</pt_156>
			<pt_157>109 220</pt_157>
			<pt_158>110 220</pt_158>
			<pt_159>111 221</pt_159>
			<pt_160>112 221</pt_160>
			<pt_161>113 221</pt_161>
			<pt_162>113 222</pt_162>
			<pt_163>114 222</pt_163>
			<pt_164>115 222</pt_164>
			<pt_165>116 222</pt_165>
			<pt_166>117 223</pt_166>
			<pt_167>118 223</pt_167>
			<pt_168>119 223</pt_168>
			<pt_169>119 223</pt_169>
			<pt_170>120 234</pt_170>
			<pt_171>120 234</pt_171>
			<pt_172>120 234</pt_172>
			<pt_173>120 234</pt_173>
			<pt_174>120 234</pt_174>
			<pt_175>120 234</pt_175>
			<pt_176>120 234</pt_176>
			<pt_177>120 234</pt_177>
			<pt_178>120 234</pt_178>
			<pt_179>120 234</pt_179>
			<pt_180>120 234</pt_180>
		</segreg>
	</segment>
	<segment>
		<name>BIRADS_2</name>
		<pose>Unspecified</pose>
		<truncated>0</truncated>
		<difficult>0</difficult>
		<count>147</count>
		<segreg>
			<pt_0>477 250</pt_0>
			<pt_1>477 251</pt_1>
			<pt_2>477 250</pt_2>
			<pt_3>477 250</pt_3>
			<pt_4>477 250</pt_4>
			<pt_5>477 250</pt_5>
			<pt_6>477 250</pt_6>
			<pt_7>477 250</pt_7>
			<pt_8>470 260</pt_8>
			<pt_9>470 261</pt_9>
			<pt_10>469 262</pt_10>
			<pt_11>469 263</pt_11>
			<pt_12>468 263</pt_12>
			<pt_13>468 264</pt_13>
			<pt_14>467 265</pt_14>
			<pt_15>466 265</pt_15>
			<pt_16>465 265</pt_16>
			<pt_17>465 266</pt_17>
			<pt_18>464 266</pt_18>
			<pt_19>463 266</pt_19>
			<pt_20>462 267</pt_20>
			<pt_21>461 267</pt_21>
			<pt_22>460 267</pt_22>
			<pt_23>459 267</pt_23>
			<pt_24>458 267</pt_24>
			<pt_25>458 268</pt_25>
			<pt_26>457 268</pt_26>
			<pt_27>456 268</pt_27>
			<pt_28>454 268</pt_28>
			<pt_29>453 268</pt_29>
			<pt_30>452 268</pt_30>
			<pt_31>450 268</pt_31>
			<pt_32>449 268</pt_32>
			<pt_33>448 268</pt_33>
			<pt_34>446 268</pt_34>
			<pt_35>445 268</pt_35>
			<pt_36>444 268</pt_36>
			<pt_37>443 268</pt_37>
			<pt_38>440 269</pt_38>
			<pt_39>439 269</pt_39>
			<pt_40>438 269</pt_40>
			<pt_41>437 269</pt_41>
			<pt_42>436 269</pt_42>
			<pt_43>435 269</pt_43>
			<pt_44>434 269</pt_44>
			<pt_45>433 269</pt_45>
			<pt_46>432 269</pt_46>
			<pt_47>431 269</pt_47>
			<pt_48>430 269</pt_48>
			<pt_49>429 269</pt_49>
			<pt_50>428 269</pt_50>
			<pt_51>427 269</pt_51>
			<pt_52>426 269</pt_52>
			<pt_53>425 268</pt_53>
			<pt_54>424 267</pt_54>
			<pt_55>423 267</pt_55>
			<pt_56>422 266</pt_56>
			<pt_57>421 265</pt_57>
			<pt_58>420 265</pt_58>
			<pt_59>420 264</pt_59>
			<pt_60>420 263</pt_60>
			<pt_61>419 262</pt_61>
			<pt_62>419 261</pt_62>
			<pt_63>419 260</pt_63>
			<pt_64>418 259</pt_64>
			<pt_65>418 258</pt_65>
			<pt_66>418 257</pt_66>
			<pt_67>417 257</pt_67>
			<pt_68>417 256</pt_68>
			<pt_69>417 255</pt_69>
			<pt_70>417 254</pt_70>
			<pt_71>417 253</pt_71>
			<pt_72>417 252</pt_72>
			<pt_73>417 251</pt_73>
			<pt_74>417 249</pt_74>
			<pt_75>417 248</pt_75>
			<pt_76>417 247</pt_76>
			<pt_77>417 247</pt_77>
			<pt_78>417 246</pt_78>
			<pt_79>417 245</pt_79>
			<pt_80>417 244</pt_80>
			<pt_81>417 243</pt_81>
			<pt_82>417 242</pt_82>
			<pt_83>418 242</pt_83>
			<pt_84>418 241</pt_84>
			<pt_85>418 240</pt_85>
			<pt_86>418 239</pt_86>
			<pt_87>418 238</pt_87>
			<pt_88>419 237</pt_88>
			<pt_89>419 236</pt_89>
			<pt_90>420 235</pt_90>
			<pt_91>421 234</pt_91>
			<pt_92>422 234</pt_92>
			<pt_93>423 233</pt_93>
			<pt_94>424 233</pt_94>
			<pt_95>425 233</pt_95>
			<pt_96>426 233</pt_96>
			<pt_97>427 233</pt_97>
			<pt_98>428 233</pt_98>
			<pt_99>429 233</pt_99>
			<pt_100>430 233</pt_100>
			<pt_101>431 233</pt_101>
			<pt_102>432 233</pt_102>
			<pt_103>433 233</pt_103>
			<pt_104>434 233</pt_104>
			<pt_105>435 233</pt_105>
			<pt_106>436 233</pt_106>
			<pt_107>437 233</pt_107>
			<pt_108>438 233</pt_108>
			<pt_109>439 233</pt_109>
			<pt_110>440 233</pt_110>
			<pt_111>441 233</pt_111>
			<pt_112>441 234</pt_112>
			<pt_113>442 234</pt_113>
			<pt_114>443 234</pt_114>
			<pt_115>444 235</pt_115>
			<pt_116>446 235</pt_116>
			<pt_117>446 236</pt_117>
			<pt_118>447 236</pt_118>
			<pt_119>448 236</pt_119>
			<pt_120>450 237</pt_120>
			<pt_121>451 237</pt_121>
			<pt_122>452 237</pt_122>
			<pt_123>453 237</pt_123>
			<pt_124>454 238</pt_124>
			<pt_125>455 238</pt_125>
			<pt_126>456 239</pt_126>
			<pt_127>457 239</pt_127>
			<pt_128>458 240</pt_128>
			<pt_129>459 240</pt_129>
			<pt_130>460 240</pt_130>
			<pt_131>461 240</pt_131>
			<pt_132>462 241</pt_132>
			<pt_133>464 242</pt_133>
			<pt_134>465 242</pt_134>
			<pt_135>466 242</pt_135>
			<pt_136>467 242</pt_136>
			<pt_137>468 242</pt_137>
			<pt_138>469 242</pt_138>
			<pt_139>477 250</pt_139>
			<pt_140>477 250</pt_140>
			<pt_141>477 250</pt_141>
			<pt_142>477 250</pt_142>
			<pt_143>477 250</pt_143>
			<pt_144>477 250</pt_144>
			<pt_145>477 250</pt_145>
			<pt_146>477 250</pt_146>
		</segreg>
	</segment>
</annotation>
