<annotation>
	<folder>2</folder>
	<filename>md0463_Image_002.jpg</filename>
	<path>C:\Users\Yuan\Desktop\mask\2\md0463_Image_002.jpg</path>
	<source>
		<database>Unknown</database>
	</source>
	<size>
		<width>880</width>
		<height>650</height>
		<depth>3</depth>
	</size>
	<segmented>0</segmented>
	<object>
		<name>BIRADS_2</name>
		<pose>Unspecified</pose>
		<truncated>0</truncated>
		<difficult>0</difficult>
		<bndbox>
			<xmin>35</xmin>
			<ymin>150</ymin>
			<xmax>235</xmax>
			<ymax>350</ymax>
		</bndbox>
	</object>
	<object>
		<name>BIRADS_2</name>
		<pose>Unspecified</pose>
		<truncated>0</truncated>
		<difficult>0</difficult>
		<bndbox>
			<xmin>485</xmin>
			<ymin>155</ymin>
			<xmax>685</xmax>
			<ymax>355</ymax>
		</bndbox>
	</object>
	<segment>
		<name>BIRADS_2</name>
		<pose>Unspecified</pose>
		<truncated>0</truncated>
		<difficult>0</difficult>
		<count>118</count>
		<segreg>
			<pt_0>147 227</pt_0>
			<pt_1>148 227</pt_1>
			<pt_2>147 227</pt_2>
			<pt_3>147 227</pt_3>
			<pt_4>147 227</pt_4>
			<pt_5>147 227</pt_5>
			<pt_6>147 227</pt_6>
			<pt_7>147 227</pt_7>
			<pt_8>147 227</pt_8>
			<pt_9>147 227</pt_9>
			<pt_10>155 235</pt_10>
			<pt_11>156 236</pt_11>
			<pt_12>157 236</pt_12>
			<pt_13>157 237</pt_13>
			<pt_14>157 238</pt_14>
			<pt_15>158 239</pt_15>
			<pt_16>158 240</pt_16>
			<pt_17>158 241</pt_17>
			<pt_18>158 242</pt_18>
			<pt_19>159 243</pt_19>
			<pt_20>159 244</pt_20>
			<pt_21>159 246</pt_21>
			<pt_22>158 246</pt_22>
			<pt_23>156 247</pt_23>
			<pt_24>155 247</pt_24>
			<pt_25>153 247</pt_25>
			<pt_26>152 247</pt_26>
			<pt_27>151 247</pt_27>
			<pt_28>150 247</pt_28>
			<pt_29>149 247</pt_29>
			<pt_30>148 247</pt_30>
			<pt_31>146 247</pt_31>
			<pt_32>145 247</pt_32>
			<pt_33>144 247</pt_33>
			<pt_34>143 247</pt_34>
			<pt_35>142 247</pt_35>
			<pt_36>141 247</pt_36>
			<pt_37>140 247</pt_37>
			<pt_38>139 247</pt_38>
			<pt_39>138 247</pt_39>
			<pt_40>137 247</pt_40>
			<pt_41>136 247</pt_41>
			<pt_42>135 247</pt_42>
			<pt_43>133 247</pt_43>
			<pt_44>132 247</pt_44>
			<pt_45>130 246</pt_45>
			<pt_46>129 246</pt_46>
			<pt_47>127 246</pt_47>
			<pt_48>126 246</pt_48>
			<pt_49>125 246</pt_49>
			<pt_50>124 246</pt_50>
			<pt_51>123 245</pt_51>
			<pt_52>122 245</pt_52>
			<pt_53>121 245</pt_53>
			<pt_54>120 245</pt_54>
			<pt_55>119 245</pt_55>
			<pt_56>119 245</pt_56>
			<pt_57>118 244</pt_57>
			<pt_58>117 244</pt_58>
			<pt_59>117 243</pt_59>
			<pt_60>115 243</pt_60>
			<pt_61>114 243</pt_61>
			<pt_62>114 242</pt_62>
			<pt_63>113 242</pt_63>
			<pt_64>112 242</pt_64>
			<pt_65>110 242</pt_65>
			<pt_66>110 241</pt_66>
			<pt_67>109 241</pt_67>
			<pt_68>108 241</pt_68>
			<pt_69>107 241</pt_69>
			<pt_70>106 241</pt_70>
			<pt_71>105 241</pt_71>
			<pt_72>104 240</pt_72>
			<pt_73>103 240</pt_73>
			<pt_74>102 240</pt_74>
			<pt_75>101 239</pt_75>
			<pt_76>101 238</pt_76>
			<pt_77>101 237</pt_77>
			<pt_78>101 235</pt_78>
			<pt_79>102 235</pt_79>
			<pt_80>103 235</pt_80>
			<pt_81>104 235</pt_81>
			<pt_82>105 235</pt_82>
			<pt_83>106 234</pt_83>
			<pt_84>107 234</pt_84>
			<pt_85>108 233</pt_85>
			<pt_86>110 233</pt_86>
			<pt_87>110 232</pt_87>
			<pt_88>112 232</pt_88>
			<pt_89>113 232</pt_89>
			<pt_90>115 232</pt_90>
			<pt_91>116 231</pt_91>
			<pt_92>117 231</pt_92>
			<pt_93>118 231</pt_93>
			<pt_94>119 231</pt_94>
			<pt_95>119 230</pt_95>
			<pt_96>120 230</pt_96>
			<pt_97>121 230</pt_97>
			<pt_98>122 229</pt_98>
			<pt_99>124 229</pt_99>
			<pt_100>125 229</pt_100>
			<pt_101>126 229</pt_101>
			<pt_102>127 229</pt_102>
			<pt_103>128 229</pt_103>
			<pt_104>129 228</pt_104>
			<pt_105>130 228</pt_105>
			<pt_106>132 228</pt_106>
			<pt_107>133 228</pt_107>
			<pt_108>134 228</pt_108>
			<pt_109>135 228</pt_109>
			<pt_110>136 228</pt_110>
			<pt_111>147 227</pt_111>
			<pt_112>147 227</pt_112>
			<pt_113>147 227</pt_113>
			<pt_114>147 227</pt_114>
			<pt_115>147 227</pt_115>
			<pt_116>147 227</pt_116>
			<pt_117>147 227</pt_117>
		</segreg>
	</segment>
	<segment>
		<name>BIRADS_2</name>
		<pose>Unspecified</pose>
		<truncated>0</truncated>
		<difficult>0</difficult>
		<count>124</count>
		<segreg>
			<pt_0>604 247</pt_0>
			<pt_1>603 247</pt_1>
			<pt_2>604 247</pt_2>
			<pt_3>604 247</pt_3>
			<pt_4>604 247</pt_4>
			<pt_5>604 247</pt_5>
			<pt_6>604 247</pt_6>
			<pt_7>604 247</pt_7>
			<pt_8>604 247</pt_8>
			<pt_9>592 248</pt_9>
			<pt_10>591 248</pt_10>
			<pt_11>589 248</pt_11>
			<pt_12>588 248</pt_12>
			<pt_13>587 248</pt_13>
			<pt_14>586 248</pt_14>
			<pt_15>585 248</pt_15>
			<pt_16>584 248</pt_16>
			<pt_17>583 248</pt_17>
			<pt_18>582 248</pt_18>
			<pt_19>581 248</pt_19>
			<pt_20>580 248</pt_20>
			<pt_21>579 248</pt_21>
			<pt_22>578 248</pt_22>
			<pt_23>577 248</pt_23>
			<pt_24>576 248</pt_24>
			<pt_25>575 248</pt_25>
			<pt_26>574 248</pt_26>
			<pt_27>573 248</pt_27>
			<pt_28>571 248</pt_28>
			<pt_29>569 248</pt_29>
			<pt_30>568 248</pt_30>
			<pt_31>566 248</pt_31>
			<pt_32>565 248</pt_32>
			<pt_33>564 248</pt_33>
			<pt_34>563 248</pt_34>
			<pt_35>562 248</pt_35>
			<pt_36>561 248</pt_36>
			<pt_37>560 247</pt_37>
			<pt_38>560 247</pt_38>
			<pt_39>560 246</pt_39>
			<pt_40>559 245</pt_40>
			<pt_41>558 244</pt_41>
			<pt_42>558 243</pt_42>
			<pt_43>558 242</pt_43>
			<pt_44>557 242</pt_44>
			<pt_45>557 241</pt_45>
			<pt_46>557 240</pt_46>
			<pt_47>557 239</pt_47>
			<pt_48>557 238</pt_48>
			<pt_49>557 237</pt_49>
			<pt_50>557 236</pt_50>
			<pt_51>557 235</pt_51>
			<pt_52>557 234</pt_52>
			<pt_53>557 233</pt_53>
			<pt_54>557 232</pt_54>
			<pt_55>558 232</pt_55>
			<pt_56>559 232</pt_56>
			<pt_57>560 232</pt_57>
			<pt_58>561 232</pt_58>
			<pt_59>563 232</pt_59>
			<pt_60>564 232</pt_60>
			<pt_61>565 231</pt_61>
			<pt_62>566 231</pt_62>
			<pt_63>566 230</pt_63>
			<pt_64>567 230</pt_64>
			<pt_65>568 230</pt_65>
			<pt_66>569 230</pt_66>
			<pt_67>570 229</pt_67>
			<pt_68>571 228</pt_68>
			<pt_69>572 228</pt_69>
			<pt_70>573 227</pt_70>
			<pt_71>574 226</pt_71>
			<pt_72>575 226</pt_72>
			<pt_73>576 226</pt_73>
			<pt_74>576 225</pt_74>
			<pt_75>577 225</pt_75>
			<pt_76>578 224</pt_76>
			<pt_77>579 223</pt_77>
			<pt_78>580 223</pt_78>
			<pt_79>581 223</pt_79>
			<pt_80>582 222</pt_80>
			<pt_81>583 222</pt_81>
			<pt_82>584 221</pt_82>
			<pt_83>585 221</pt_83>
			<pt_84>586 221</pt_84>
			<pt_85>587 221</pt_85>
			<pt_86>588 221</pt_86>
			<pt_87>589 221</pt_87>
			<pt_88>590 221</pt_88>
			<pt_89>591 221</pt_89>
			<pt_90>593 221</pt_90>
			<pt_91>593 222</pt_91>
			<pt_92>594 222</pt_92>
			<pt_93>595 224</pt_93>
			<pt_94>596 224</pt_94>
			<pt_95>596 225</pt_95>
			<pt_96>597 225</pt_96>
			<pt_97>597 226</pt_97>
			<pt_98>598 226</pt_98>
			<pt_99>599 227</pt_99>
			<pt_100>600 228</pt_100>
			<pt_101>601 229</pt_101>
			<pt_102>602 230</pt_102>
			<pt_103>603 230</pt_103>
			<pt_104>603 231</pt_104>
			<pt_105>604 232</pt_105>
			<pt_106>604 233</pt_106>
			<pt_107>605 233</pt_107>
			<pt_108>605 234</pt_108>
			<pt_109>606 234</pt_109>
			<pt_110>607 235</pt_110>
			<pt_111>607 236</pt_111>
			<pt_112>608 236</pt_112>
			<pt_113>604 247</pt_113>
			<pt_114>609 237</pt_114>
			<pt_115>604 247</pt_115>
			<pt_116>604 247</pt_116>
			<pt_117>604 247</pt_117>
			<pt_118>604 247</pt_118>
			<pt_119>604 247</pt_119>
			<pt_120>604 247</pt_120>
			<pt_121>604 247</pt_121>
			<pt_122>604 247</pt_122>
			<pt_123>604 247</pt_123>
		</segreg>
	</segment>
</annotation>
