<annotation>
	<folder>3 _unsplist</folder>
	<filename>md0434_Image_009.jpg</filename>
	<path>D:\image data modify\problem\mask class\3 _unsplist\md0434_Image_009.jpg</path>
	<source>
		<database>Unknown</database>
	</source>
	<size>
		<width>880</width>
		<height>650</height>
		<depth>3</depth>
	</size>
	<segmented>0</segmented>
	<object>
		<name>BIRADS_4</name>
		<pose>Unspecified</pose>
		<truncated>0</truncated>
		<difficult>0</difficult>
		<bndbox>
			<xmin>77</xmin>
			<ymin>151</ymin>
			<xmax>277</xmax>
			<ymax>351</ymax>
		</bndbox>
	</object>
	<object>
		<name>BIRADS_3</name>
		<pose>Unspecified</pose>
		<truncated>0</truncated>
		<difficult>0</difficult>
		<bndbox>
			<xmin>385</xmin>
			<ymin>172</ymin>
			<xmax>585</xmax>
			<ymax>372</ymax>
		</bndbox>
	</object>
	<segment>
		<name>BIRADS_4</name>
		<pose>Unspecified</pose>
		<truncated>0</truncated>
		<difficult>0</difficult>
		<count>325</count>
		<segreg>
			<pt_0>270 217</pt_0>
			<pt_1>269 217</pt_1>
			<pt_2>270 217</pt_2>
			<pt_3>270 217</pt_3>
			<pt_4>270 217</pt_4>
			<pt_5>270 217</pt_5>
			<pt_6>259 224</pt_6>
			<pt_7>256 225</pt_7>
			<pt_8>255 225</pt_8>
			<pt_9>254 226</pt_9>
			<pt_10>253 226</pt_10>
			<pt_11>252 226</pt_11>
			<pt_12>252 227</pt_12>
			<pt_13>251 228</pt_13>
			<pt_14>250 229</pt_14>
			<pt_15>249 229</pt_15>
			<pt_16>248 229</pt_16>
			<pt_17>247 229</pt_17>
			<pt_18>246 229</pt_18>
			<pt_19>245 229</pt_19>
			<pt_20>243 229</pt_20>
			<pt_21>242 229</pt_21>
			<pt_22>240 229</pt_22>
			<pt_23>239 229</pt_23>
			<pt_24>237 229</pt_24>
			<pt_25>236 229</pt_25>
			<pt_26>235 229</pt_26>
			<pt_27>234 229</pt_27>
			<pt_28>233 229</pt_28>
			<pt_29>232 229</pt_29>
			<pt_30>230 230</pt_30>
			<pt_31>229 231</pt_31>
			<pt_32>228 232</pt_32>
			<pt_33>226 232</pt_33>
			<pt_34>224 233</pt_34>
			<pt_35>222 234</pt_35>
			<pt_36>221 234</pt_36>
			<pt_37>218 234</pt_37>
			<pt_38>217 234</pt_38>
			<pt_39>216 235</pt_39>
			<pt_40>215 235</pt_40>
			<pt_41>214 236</pt_41>
			<pt_42>213 236</pt_42>
			<pt_43>212 236</pt_43>
			<pt_44>212 237</pt_44>
			<pt_45>211 237</pt_45>
			<pt_46>210 237</pt_46>
			<pt_47>209 237</pt_47>
			<pt_48>208 237</pt_48>
			<pt_49>208 238</pt_49>
			<pt_50>207 238</pt_50>
			<pt_51>206 238</pt_51>
			<pt_52>204 239</pt_52>
			<pt_53>203 239</pt_53>
			<pt_54>200 240</pt_54>
			<pt_55>198 240</pt_55>
			<pt_56>196 241</pt_56>
			<pt_57>195 241</pt_57>
			<pt_58>193 242</pt_58>
			<pt_59>192 242</pt_59>
			<pt_60>190 243</pt_60>
			<pt_61>189 243</pt_61>
			<pt_62>187 243</pt_62>
			<pt_63>186 243</pt_63>
			<pt_64>185 243</pt_64>
			<pt_65>184 243</pt_65>
			<pt_66>183 243</pt_66>
			<pt_67>182 243</pt_67>
			<pt_68>181 244</pt_68>
			<pt_69>180 244</pt_69>
			<pt_70>179 244</pt_70>
			<pt_71>178 244</pt_71>
			<pt_72>177 244</pt_72>
			<pt_73>174 245</pt_73>
			<pt_74>172 245</pt_74>
			<pt_75>171 246</pt_75>
			<pt_76>169 247</pt_76>
			<pt_77>167 247</pt_77>
			<pt_78>166 247</pt_78>
			<pt_79>165 247</pt_79>
			<pt_80>163 247</pt_80>
			<pt_81>161 247</pt_81>
			<pt_82>160 248</pt_82>
			<pt_83>159 248</pt_83>
			<pt_84>158 248</pt_84>
			<pt_85>157 248</pt_85>
			<pt_86>156 248</pt_86>
			<pt_87>155 248</pt_87>
			<pt_88>154 248</pt_88>
			<pt_89>152 248</pt_89>
			<pt_90>151 248</pt_90>
			<pt_91>150 248</pt_91>
			<pt_92>147 248</pt_92>
			<pt_93>147 247</pt_93>
			<pt_94>146 246</pt_94>
			<pt_95>145 244</pt_95>
			<pt_96>144 244</pt_96>
			<pt_97>143 244</pt_97>
			<pt_98>142 244</pt_98>
			<pt_99>141 244</pt_99>
			<pt_100>139 243</pt_100>
			<pt_101>136 242</pt_101>
			<pt_102>135 242</pt_102>
			<pt_103>133 241</pt_103>
			<pt_104>131 240</pt_104>
			<pt_105>129 240</pt_105>
			<pt_106>128 240</pt_106>
			<pt_107>125 239</pt_107>
			<pt_108>123 238</pt_108>
			<pt_109>121 238</pt_109>
			<pt_110>120 238</pt_110>
			<pt_111>118 238</pt_111>
			<pt_112>115 236</pt_112>
			<pt_113>114 235</pt_113>
			<pt_114>113 235</pt_114>
			<pt_115>112 235</pt_115>
			<pt_116>111 235</pt_116>
			<pt_117>110 234</pt_117>
			<pt_118>108 233</pt_118>
			<pt_119>107 233</pt_119>
			<pt_120>106 233</pt_120>
			<pt_121>106 232</pt_121>
			<pt_122>105 232</pt_122>
			<pt_123>104 232</pt_123>
			<pt_124>103 232</pt_124>
			<pt_125>103 231</pt_125>
			<pt_126>102 230</pt_126>
			<pt_127>101 230</pt_127>
			<pt_128>100 230</pt_128>
			<pt_129>99 229</pt_129>
			<pt_130>98 229</pt_130>
			<pt_131>96 229</pt_131>
			<pt_132>95 229</pt_132>
			<pt_133>94 228</pt_133>
			<pt_134>93 227</pt_134>
			<pt_135>92 227</pt_135>
			<pt_136>91 227</pt_136>
			<pt_137>90 226</pt_137>
			<pt_138>89 226</pt_138>
			<pt_139>87 225</pt_139>
			<pt_140>86 224</pt_140>
			<pt_141>85 223</pt_141>
			<pt_142>84 221</pt_142>
			<pt_143>84 220</pt_143>
			<pt_144>84 219</pt_144>
			<pt_145>84 218</pt_145>
			<pt_146>85 218</pt_146>
			<pt_147>85 217</pt_147>
			<pt_148>86 217</pt_148>
			<pt_149>87 217</pt_149>
			<pt_150>89 217</pt_150>
			<pt_151>91 217</pt_151>
			<pt_152>91 216</pt_152>
			<pt_153>92 216</pt_153>
			<pt_154>93 215</pt_154>
			<pt_155>94 215</pt_155>
			<pt_156>95 215</pt_156>
			<pt_157>96 215</pt_157>
			<pt_158>97 215</pt_158>
			<pt_159>98 214</pt_159>
			<pt_160>99 214</pt_160>
			<pt_161>100 214</pt_161>
			<pt_162>101 214</pt_162>
			<pt_163>102 214</pt_163>
			<pt_164>104 214</pt_164>
			<pt_165>105 213</pt_165>
			<pt_166>106 213</pt_166>
			<pt_167>107 212</pt_167>
			<pt_168>108 212</pt_168>
			<pt_169>108 211</pt_169>
			<pt_170>109 211</pt_170>
			<pt_171>110 211</pt_171>
			<pt_172>112 211</pt_172>
			<pt_173>113 211</pt_173>
			<pt_174>114 211</pt_174>
			<pt_175>116 211</pt_175>
			<pt_176>118 210</pt_176>
			<pt_177>119 210</pt_177>
			<pt_178>120 210</pt_178>
			<pt_179>121 209</pt_179>
			<pt_180>122 209</pt_180>
			<pt_181>123 208</pt_181>
			<pt_182>124 208</pt_182>
			<pt_183>124 207</pt_183>
			<pt_184>125 206</pt_184>
			<pt_185>125 205</pt_185>
			<pt_186>127 204</pt_186>
			<pt_187>127 203</pt_187>
			<pt_188>128 203</pt_188>
			<pt_189>128 202</pt_189>
			<pt_190>129 202</pt_190>
			<pt_191>129 201</pt_191>
			<pt_192>131 200</pt_192>
			<pt_193>132 200</pt_193>
			<pt_194>133 199</pt_194>
			<pt_195>134 199</pt_195>
			<pt_196>135 198</pt_196>
			<pt_197>135 197</pt_197>
			<pt_198>136 197</pt_198>
			<pt_199>137 197</pt_199>
			<pt_200>139 196</pt_200>
			<pt_201>140 196</pt_201>
			<pt_202>141 196</pt_202>
			<pt_203>142 196</pt_203>
			<pt_204>143 196</pt_204>
			<pt_205>144 196</pt_205>
			<pt_206>145 196</pt_206>
			<pt_207>146 196</pt_207>
			<pt_208>147 196</pt_208>
			<pt_209>148 196</pt_209>
			<pt_210>149 196</pt_210>
			<pt_211>150 196</pt_211>
			<pt_212>151 196</pt_212>
			<pt_213>152 196</pt_213>
			<pt_214>153 196</pt_214>
			<pt_215>154 196</pt_215>
			<pt_216>155 196</pt_216>
			<pt_217>156 196</pt_217>
			<pt_218>157 196</pt_218>
			<pt_219>158 196</pt_219>
			<pt_220>159 196</pt_220>
			<pt_221>160 196</pt_221>
			<pt_222>161 196</pt_222>
			<pt_223>162 196</pt_223>
			<pt_224>163 196</pt_224>
			<pt_225>164 196</pt_225>
			<pt_226>166 196</pt_226>
			<pt_227>167 196</pt_227>
			<pt_228>169 196</pt_228>
			<pt_229>170 196</pt_229>
			<pt_230>172 196</pt_230>
			<pt_231>173 196</pt_231>
			<pt_232>174 196</pt_232>
			<pt_233>175 196</pt_233>
			<pt_234>177 196</pt_234>
			<pt_235>178 197</pt_235>
			<pt_236>179 197</pt_236>
			<pt_237>180 197</pt_237>
			<pt_238>180 198</pt_238>
			<pt_239>181 198</pt_239>
			<pt_240>182 198</pt_240>
			<pt_241>182 199</pt_241>
			<pt_242>183 199</pt_242>
			<pt_243>184 199</pt_243>
			<pt_244>184 200</pt_244>
			<pt_245>185 201</pt_245>
			<pt_246>186 201</pt_246>
			<pt_247>186 202</pt_247>
			<pt_248>187 202</pt_248>
			<pt_249>189 203</pt_249>
			<pt_250>190 203</pt_250>
			<pt_251>191 204</pt_251>
			<pt_252>192 205</pt_252>
			<pt_253>193 205</pt_253>
			<pt_254>194 205</pt_254>
			<pt_255>195 205</pt_255>
			<pt_256>196 205</pt_256>
			<pt_257>197 205</pt_257>
			<pt_258>198 205</pt_258>
			<pt_259>200 205</pt_259>
			<pt_260>202 205</pt_260>
			<pt_261>204 205</pt_261>
			<pt_262>206 205</pt_262>
			<pt_263>208 205</pt_263>
			<pt_264>209 205</pt_264>
			<pt_265>210 205</pt_265>
			<pt_266>211 205</pt_266>
			<pt_267>212 205</pt_267>
			<pt_268>213 205</pt_268>
			<pt_269>214 205</pt_269>
			<pt_270>215 205</pt_270>
			<pt_271>216 204</pt_271>
			<pt_272>217 204</pt_272>
			<pt_273>218 204</pt_273>
			<pt_274>219 204</pt_274>
			<pt_275>220 204</pt_275>
			<pt_276>221 204</pt_276>
			<pt_277>222 204</pt_277>
			<pt_278>223 203</pt_278>
			<pt_279>224 203</pt_279>
			<pt_280>225 203</pt_280>
			<pt_281>226 203</pt_281>
			<pt_282>227 203</pt_282>
			<pt_283>228 203</pt_283>
			<pt_284>230 203</pt_284>
			<pt_285>231 203</pt_285>
			<pt_286>232 203</pt_286>
			<pt_287>233 203</pt_287>
			<pt_288>234 203</pt_288>
			<pt_289>235 203</pt_289>
			<pt_290>236 203</pt_290>
			<pt_291>237 204</pt_291>
			<pt_292>239 205</pt_292>
			<pt_293>240 205</pt_293>
			<pt_294>240 206</pt_294>
			<pt_295>241 206</pt_295>
			<pt_296>242 207</pt_296>
			<pt_297>242 208</pt_297>
			<pt_298>243 208</pt_298>
			<pt_299>244 209</pt_299>
			<pt_300>245 209</pt_300>
			<pt_301>245 210</pt_301>
			<pt_302>246 210</pt_302>
			<pt_303>246 211</pt_303>
			<pt_304>247 212</pt_304>
			<pt_305>249 212</pt_305>
			<pt_306>249 213</pt_306>
			<pt_307>250 213</pt_307>
			<pt_308>251 213</pt_308>
			<pt_309>252 213</pt_309>
			<pt_310>253 213</pt_310>
			<pt_311>254 213</pt_311>
			<pt_312>255 213</pt_312>
			<pt_313>256 213</pt_313>
			<pt_314>257 213</pt_314>
			<pt_315>258 213</pt_315>
			<pt_316>259 213</pt_316>
			<pt_317>270 217</pt_317>
			<pt_318>270 217</pt_318>
			<pt_319>270 217</pt_319>
			<pt_320>270 217</pt_320>
			<pt_321>270 217</pt_321>
			<pt_322>270 217</pt_322>
			<pt_323>270 217</pt_323>
			<pt_324>270 217</pt_324>
		</segreg>
	</segment>
	<segment>
		<name>BIRADS_3</name>
		<pose>Unspecified</pose>
		<truncated>0</truncated>
		<difficult>0</difficult>
		<count>237</count>
		<segreg>
			<pt_0>559 221</pt_0>
			<pt_1>558 221</pt_1>
			<pt_2>559 221</pt_2>
			<pt_3>559 221</pt_3>
			<pt_4>559 221</pt_4>
			<pt_5>559 221</pt_5>
			<pt_6>552 230</pt_6>
			<pt_7>551 231</pt_7>
			<pt_8>551 232</pt_8>
			<pt_9>550 233</pt_9>
			<pt_10>549 234</pt_10>
			<pt_11>549 235</pt_11>
			<pt_12>548 236</pt_12>
			<pt_13>547 236</pt_13>
			<pt_14>547 237</pt_14>
			<pt_15>547 238</pt_15>
			<pt_16>546 239</pt_16>
			<pt_17>546 240</pt_17>
			<pt_18>545 240</pt_18>
			<pt_19>545 241</pt_19>
			<pt_20>543 242</pt_20>
			<pt_21>541 243</pt_21>
			<pt_22>540 244</pt_22>
			<pt_23>539 245</pt_23>
			<pt_24>537 245</pt_24>
			<pt_25>536 246</pt_25>
			<pt_26>535 247</pt_26>
			<pt_27>534 247</pt_27>
			<pt_28>533 247</pt_28>
			<pt_29>533 248</pt_29>
			<pt_30>531 248</pt_30>
			<pt_31>530 248</pt_31>
			<pt_32>529 248</pt_32>
			<pt_33>528 248</pt_33>
			<pt_34>526 249</pt_34>
			<pt_35>525 249</pt_35>
			<pt_36>524 249</pt_36>
			<pt_37>523 249</pt_37>
			<pt_38>522 249</pt_38>
			<pt_39>521 249</pt_39>
			<pt_40>520 249</pt_40>
			<pt_41>519 249</pt_41>
			<pt_42>518 249</pt_42>
			<pt_43>517 249</pt_43>
			<pt_44>516 249</pt_44>
			<pt_45>514 249</pt_45>
			<pt_46>513 249</pt_46>
			<pt_47>511 249</pt_47>
			<pt_48>510 249</pt_48>
			<pt_49>508 249</pt_49>
			<pt_50>505 249</pt_50>
			<pt_51>503 249</pt_51>
			<pt_52>501 249</pt_52>
			<pt_53>500 249</pt_53>
			<pt_54>499 249</pt_54>
			<pt_55>497 249</pt_55>
			<pt_56>496 249</pt_56>
			<pt_57>494 249</pt_57>
			<pt_58>493 249</pt_58>
			<pt_59>492 249</pt_59>
			<pt_60>491 249</pt_60>
			<pt_61>490 249</pt_61>
			<pt_62>487 249</pt_62>
			<pt_63>486 249</pt_63>
			<pt_64>485 248</pt_64>
			<pt_65>484 248</pt_65>
			<pt_66>483 247</pt_66>
			<pt_67>482 246</pt_67>
			<pt_68>481 246</pt_68>
			<pt_69>479 245</pt_69>
			<pt_70>477 245</pt_70>
			<pt_71>476 244</pt_71>
			<pt_72>474 243</pt_72>
			<pt_73>473 243</pt_73>
			<pt_74>473 242</pt_74>
			<pt_75>472 242</pt_75>
			<pt_76>471 241</pt_76>
			<pt_77>470 241</pt_77>
			<pt_78>469 240</pt_78>
			<pt_79>467 239</pt_79>
			<pt_80>466 238</pt_80>
			<pt_81>464 238</pt_81>
			<pt_82>462 237</pt_82>
			<pt_83>461 237</pt_83>
			<pt_84>460 236</pt_84>
			<pt_85>458 236</pt_85>
			<pt_86>457 235</pt_86>
			<pt_87>456 235</pt_87>
			<pt_88>455 235</pt_88>
			<pt_89>454 234</pt_89>
			<pt_90>454 233</pt_90>
			<pt_91>453 233</pt_91>
			<pt_92>451 231</pt_92>
			<pt_93>450 230</pt_93>
			<pt_94>449 229</pt_94>
			<pt_95>448 228</pt_95>
			<pt_96>447 228</pt_96>
			<pt_97>447 227</pt_97>
			<pt_98>446 226</pt_98>
			<pt_99>446 225</pt_99>
			<pt_100>444 223</pt_100>
			<pt_101>444 221</pt_101>
			<pt_102>443 221</pt_102>
			<pt_103>443 220</pt_103>
			<pt_104>443 219</pt_104>
			<pt_105>443 218</pt_105>
			<pt_106>443 217</pt_106>
			<pt_107>442 217</pt_107>
			<pt_108>442 216</pt_108>
			<pt_109>441 216</pt_109>
			<pt_110>441 215</pt_110>
			<pt_111>441 214</pt_111>
			<pt_112>441 213</pt_112>
			<pt_113>441 212</pt_113>
			<pt_114>441 211</pt_114>
			<pt_115>442 210</pt_115>
			<pt_116>443 209</pt_116>
			<pt_117>444 209</pt_117>
			<pt_118>445 209</pt_118>
			<pt_119>446 209</pt_119>
			<pt_120>447 208</pt_120>
			<pt_121>448 208</pt_121>
			<pt_122>449 207</pt_122>
			<pt_123>450 207</pt_123>
			<pt_124>452 206</pt_124>
			<pt_125>453 206</pt_125>
			<pt_126>455 205</pt_126>
			<pt_127>456 204</pt_127>
			<pt_128>458 204</pt_128>
			<pt_129>459 203</pt_129>
			<pt_130>461 202</pt_130>
			<pt_131>463 202</pt_131>
			<pt_132>464 202</pt_132>
			<pt_133>466 201</pt_133>
			<pt_134>467 201</pt_134>
			<pt_135>468 201</pt_135>
			<pt_136>469 200</pt_136>
			<pt_137>470 200</pt_137>
			<pt_138>470 199</pt_138>
			<pt_139>471 199</pt_139>
			<pt_140>472 199</pt_140>
			<pt_141>473 199</pt_141>
			<pt_142>474 199</pt_142>
			<pt_143>474 198</pt_143>
			<pt_144>475 198</pt_144>
			<pt_145>475 197</pt_145>
			<pt_146>476 197</pt_146>
			<pt_147>477 197</pt_147>
			<pt_148>478 197</pt_148>
			<pt_149>480 196</pt_149>
			<pt_150>481 196</pt_150>
			<pt_151>482 195</pt_151>
			<pt_152>484 194</pt_152>
			<pt_153>485 194</pt_153>
			<pt_154>486 193</pt_154>
			<pt_155>487 192</pt_155>
			<pt_156>489 192</pt_156>
			<pt_157>490 191</pt_157>
			<pt_158>491 191</pt_158>
			<pt_159>492 191</pt_159>
			<pt_160>493 190</pt_160>
			<pt_161>494 190</pt_161>
			<pt_162>495 189</pt_162>
			<pt_163>496 189</pt_163>
			<pt_164>498 189</pt_164>
			<pt_165>499 188</pt_165>
			<pt_166>500 188</pt_166>
			<pt_167>501 188</pt_167>
			<pt_168>502 188</pt_168>
			<pt_169>503 188</pt_169>
			<pt_170>504 187</pt_170>
			<pt_171>505 187</pt_171>
			<pt_172>506 187</pt_172>
			<pt_173>507 187</pt_173>
			<pt_174>508 187</pt_174>
			<pt_175>509 187</pt_175>
			<pt_176>509 186</pt_176>
			<pt_177>510 186</pt_177>
			<pt_178>511 186</pt_178>
			<pt_179>511 185</pt_179>
			<pt_180>512 185</pt_180>
			<pt_181>513 185</pt_181>
			<pt_182>514 184</pt_182>
			<pt_183>515 184</pt_183>
			<pt_184>516 184</pt_184>
			<pt_185>517 184</pt_185>
			<pt_186>519 184</pt_186>
			<pt_187>520 184</pt_187>
			<pt_188>522 184</pt_188>
			<pt_189>523 184</pt_189>
			<pt_190>524 184</pt_190>
			<pt_191>525 184</pt_191>
			<pt_192>526 184</pt_192>
			<pt_193>527 184</pt_193>
			<pt_194>528 184</pt_194>
			<pt_195>529 185</pt_195>
			<pt_196>530 185</pt_196>
			<pt_197>530 186</pt_197>
			<pt_198>531 187</pt_198>
			<pt_199>532 188</pt_199>
			<pt_200>533 189</pt_200>
			<pt_201>534 190</pt_201>
			<pt_202>534 191</pt_202>
			<pt_203>535 191</pt_203>
			<pt_204>535 192</pt_204>
			<pt_205>536 193</pt_205>
			<pt_206>537 194</pt_206>
			<pt_207>537 195</pt_207>
			<pt_208>539 195</pt_208>
			<pt_209>539 196</pt_209>
			<pt_210>540 196</pt_210>
			<pt_211>540 197</pt_211>
			<pt_212>541 197</pt_212>
			<pt_213>541 198</pt_213>
			<pt_214>543 199</pt_214>
			<pt_215>543 200</pt_215>
			<pt_216>544 200</pt_216>
			<pt_217>545 202</pt_217>
			<pt_218>546 202</pt_218>
			<pt_219>546 203</pt_219>
			<pt_220>548 203</pt_220>
			<pt_221>548 204</pt_221>
			<pt_222>549 205</pt_222>
			<pt_223>551 206</pt_223>
			<pt_224>553 206</pt_224>
			<pt_225>553 207</pt_225>
			<pt_226>554 208</pt_226>
			<pt_227>555 208</pt_227>
			<pt_228>555 209</pt_228>
			<pt_229>556 210</pt_229>
			<pt_230>559 221</pt_230>
			<pt_231>559 221</pt_231>
			<pt_232>559 221</pt_232>
			<pt_233>559 221</pt_233>
			<pt_234>559 221</pt_234>
			<pt_235>559 221</pt_235>
			<pt_236>559 221</pt_236>
		</segreg>
	</segment>
</annotation>
